pycord/quart/__init__.py
pycord/quart/auth.py
pycord/quart/decorators.py
pycord/quart/exceptions.py
pycord/quart/py.typed
pycord/quart/status.py
pycord_quart-0.1.4.dist-info/licenses/LICENSE
pycord_quart-0.1.4.dist-info/METADATA
pycord_quart-0.1.4.dist-info/WHEEL
pycord_quart-0.1.4.dist-info/top_level.txt
pycord_quart-0.1.4.dist-info/RECORD
